LICENSE
README.md
setup.py
maha_tts/__init__.py
maha_tts/config.py
maha_tts/inference.py
maha_tts.egg-info/PKG-INFO
maha_tts.egg-info/SOURCES.txt
maha_tts.egg-info/dependency_links.txt
maha_tts.egg-info/requires.txt
maha_tts.egg-info/top_level.txt
maha_tts/dataloaders/__init__.py
maha_tts/models/__init__.py
maha_tts/models/autoregressive.py
maha_tts/models/diff_model.py
maha_tts/models/modules.py
maha_tts/models/vocoder.py
maha_tts/text/__init__.py
maha_tts/text/cleaners.py
maha_tts/text/symbols.py
maha_tts/utils/__init__.py
maha_tts/utils/audio.py
maha_tts/utils/diffusion.py
maha_tts/utils/stft.py