Metadata-Version: 2.1
Name: maha-tts
Version: 1.0.0
Home-page: https://github.com/dubverse-ai/MahaTTS/tree/main
Author: Dubverse AI
Author-email: jaskaran@dubverse.ai
License-File: LICENSE
Requires-Dist: einops
Requires-Dist: transformers
Requires-Dist: unidecode
Requires-Dist: inflect
